Metadata-Version: 2.1
Name: music-x
Version: 5.1.10
Summary: Music Assistant
Author-email: The Music Assistant Authors <marcelveldt@users.noreply.github.com>
License: Apache-2.0
Platform: any
Classifier: Environment :: Console
Classifier: Programming Language :: Python :: 3.11
Classifier: Programming Language :: Python :: 3.12
Requires-Python: >=3.11
License-File: LICENSE
Requires-Dist: aiohttp
Requires-Dist: orjson
Requires-Dist: mashumaro
Provides-Extra: server
Requires-Dist: faust-cchardet >=2.1.18 ; extra == 'server'
Requires-Dist: aiodns >=3.0.0 ; extra == 'server'
Requires-Dist: Brotli >=1.0.9 ; extra == 'server'
Requires-Dist: aiohttp ==3.9.5 ; extra == 'server'
Requires-Dist: asyncio-throttle ==1.0.2 ; extra == 'server'
Requires-Dist: aiofiles ==24.1.0 ; extra == 'server'
Requires-Dist: aiorun ==2024.5.1 ; extra == 'server'
Requires-Dist: certifi ==2024.7.4 ; extra == 'server'
Requires-Dist: colorlog ==6.8.2 ; extra == 'server'
Requires-Dist: aiosqlite ==0.20.0 ; extra == 'server'
Requires-Dist: eyeD3 ==0.9.7 ; extra == 'server'
Requires-Dist: python-slugify ==8.0.4 ; extra == 'server'
Requires-Dist: mashumaro ==3.13.1 ; extra == 'server'
Requires-Dist: memory-tempfile ==2.2.3 ; extra == 'server'
Requires-Dist: music-assistant-frontend ==2.5.15 ; extra == 'server'
Requires-Dist: pillow ==10.4.0 ; extra == 'server'
Requires-Dist: unidecode ==1.3.8 ; extra == 'server'
Requires-Dist: xmltodict ==0.13.0 ; extra == 'server'
Requires-Dist: orjson ==3.10.5 ; extra == 'server'
Requires-Dist: shortuuid ==1.0.13 ; extra == 'server'
Requires-Dist: zeroconf ==0.132.2 ; extra == 'server'
Requires-Dist: cryptography ==42.0.8 ; extra == 'server'
Requires-Dist: ifaddr ==0.2.0 ; extra == 'server'
Provides-Extra: test
Requires-Dist: codespell ==2.3.0 ; extra == 'test'
Requires-Dist: isort ==5.13.2 ; extra == 'test'
Requires-Dist: mypy ==1.10.1 ; extra == 'test'
Requires-Dist: pre-commit ==3.7.1 ; extra == 'test'
Requires-Dist: pre-commit-hooks ==4.6.0 ; extra == 'test'
Requires-Dist: pylint ==3.2.5 ; extra == 'test'
Requires-Dist: pytest ==8.2.2 ; extra == 'test'
Requires-Dist: pytest-aiohttp ==1.0.5 ; extra == 'test'
Requires-Dist: pytest-cov ==5.0.0 ; extra == 'test'
Requires-Dist: syrupy ==4.6.1 ; extra == 'test'
Requires-Dist: tomli ==2.0.1 ; extra == 'test'
Requires-Dist: ruff ==0.5.0 ; extra == 'test'
